MANIFEST.in
README.md
setup.py
graphene_sqlalchemy_autocrud/__init__.py
graphene_sqlalchemy_autocrud.egg-info/PKG-INFO
graphene_sqlalchemy_autocrud.egg-info/SOURCES.txt
graphene_sqlalchemy_autocrud.egg-info/dependency_links.txt
graphene_sqlalchemy_autocrud.egg-info/requires.txt
graphene_sqlalchemy_autocrud.egg-info/top_level.txt