Metadata-Version: 1.0
Name: graphene-sqlalchemy-autocrud
Version: 0.0.2
Summary: Tools for automatically building GraphQL query resolvers and mutations from SQLAlchemy models
Home-page: https://github.com/harvestport/graphene_sqlalchemy_autocrud
Author: Brent Tubbs
Author-email: brent.tubbs@gmail.com
License: UNKNOWN
Platform: UNKNOWN
